crowds/__init__.py
crowds/kanonymity/__init__.py
crowds/kanonymity/generalizations.py
crowds/kanonymity/information_loss.py
crowds/kanonymity/lattice.py
crowds/kanonymity/ola.py
crowds/kanonymity/utils.py
crowds-0.0.1.dist-info/LICENSE
crowds-0.0.1.dist-info/METADATA
crowds-0.0.1.dist-info/WHEEL
crowds-0.0.1.dist-info/top_level.txt
crowds-0.0.1.dist-info/RECORD
