Metadata-Version: 2.1
Name: crowds
Version: 0.0.1
Summary: A collection of anonymization algorithms in Python 
Home-page: https://github.com/leo-mazz/crowds
Author: Leonardo Mazzone
Author-email: leo@mazzone.space
License: GNU Affero General Public License v3.0
Platform: UNKNOWN
Requires-Dist: pandas (>=0.25.1)
